optenum/__init__.py
optenum/mysix.py
optenum/option.py
optenum/option.v1.py
optenum/options.py
optenum/version.py
optenum-1.1.9.dist-info/LICENSE
optenum-1.1.9.dist-info/METADATA
optenum-1.1.9.dist-info/WHEEL
optenum-1.1.9.dist-info/top_level.txt
optenum-1.1.9.dist-info/RECORD
