Metadata-Version: 2.1
Name: optenum
Version: 1.1.9
Summary: A missing Python Option/Enum library
Home-page: http://en.samuelchen.net/project/optenum/
Author: Samuel Chen
Author-email: samuel.net@gmail.com
Project-URL: Bug Reports, https://github.com/samuelchen/optenum/issues
Project-URL: Source, https://github.com/samuelchen/optenum
Keywords: enum library development
Classifier: Development Status :: 5 - Production/Stable
Classifier: Intended Audience :: Developers
Classifier: Topic :: Software Development :: Libraries :: Python Modules
Classifier: License :: OSI Approved :: MIT License
Classifier: Programming Language :: Python :: 2
Classifier: Programming Language :: Python :: 2.7
Classifier: Programming Language :: Python :: 3
Classifier: Programming Language :: Python :: 3.4
Classifier: Programming Language :: Python :: 3.5
Classifier: Programming Language :: Python :: 3.6
Classifier: Programming Language :: Python :: 3.7
Requires-Python: >=2.7, !=3.0.*, !=3.1.*, !=3.2.*, !=3.3.*, <4
License-File: LICENSE
Requires-Dist: six
Provides-Extra: dev
Requires-Dist: check-manifest ; extra == 'dev'
Provides-Extra: test
Requires-Dist: coverage ; extra == 'test'
